README.rst
setup.py
strings2pot/__init__.py
strings2pot/strings2pot.py
strings2pot.egg-info/PKG-INFO
strings2pot.egg-info/SOURCES.txt
strings2pot.egg-info/dependency_links.txt
strings2pot.egg-info/entry_points.txt
strings2pot.egg-info/not-zip-safe
strings2pot.egg-info/top_level.txt
strings2pot/extractors/__init__.py
strings2pot/extractors/android.py
strings2pot/extractors/android_test.py
strings2pot/extractors/arb.py
strings2pot/extractors/arb_test.py
strings2pot/extractors/ios.py
strings2pot/extractors/ios_test.py