Metadata-Version: 1.1
Name: strings2pot
Version: 0.3.5
Summary: Converts Apple .strings, Android/Java .xml or Google app resource bundle .arb files to POT gettext files.
Home-page: http://qurami.com/
Author: Gianfranco Reppucci
Author-email: gianfranco.reppucci@qurami.com
License: MIT
Platform: UNKNOWN
Classifier: Development Status :: 4 - Beta
Classifier: Environment :: Web Environment
Classifier: Intended Audience :: Developers
Classifier: License :: OSI Approved :: MIT License
Classifier: Operating System :: OS Independent
Classifier: Programming Language :: Python
Classifier: Programming Language :: Python :: 2.6
Classifier: Programming Language :: Python :: 2.7
Classifier: Topic :: Software Development :: Libraries :: Python Modules
